pubmedclient/__init__.py
pubmedclient/models.py
pubmedclient/sdk.py
pubmedclient-0.2.0.dist-info/METADATA
pubmedclient-0.2.0.dist-info/WHEEL
pubmedclient-0.2.0.dist-info/licenses/LICENSE
pubmedclient-0.2.0.dist-info/RECORD
