Metadata-Version: 2.4
Name: pubmedclient
Version: 0.2.0
Summary: Add your description here
License-File: LICENSE
Requires-Python: >=3.12
Requires-Dist: httpx>=0.28.1
Requires-Dist: pydantic>=2.10.4
